[{"viewminutes":859921620,"streamedminutes":9138060,"uniquechannels":23393,"year":2016,"month":"january","language":"241"},{"viewminutes":839085180,"streamedminutes":8581980,"uniquechannels":24694,"year":2016,"month":"february","language":"241"},{"viewminutes":875053020,"streamedminutes":9121680,"uniquechannels":24904,"year":2016,"month":"march","language":"241"},{"viewminutes":836978940,"streamedminutes":8082300,"uniquechannels":24908,"year":2016,"month":"april","language":"241"},{"viewminutes":824379480,"streamedminutes":9596880,"uniquechannels":27350,"year":2016,"month":"may","language":"241"},{"viewminutes":825808980,"streamedminutes":7524840,"uniquechannels":26253,"year":2016,"month":"june","language":"241"},{"viewminutes":954978360,"streamedminutes":10587120,"uniquechannels":29399,"year":2016,"month":"july","language":"241"},{"viewminutes":927379080,"streamedminutes":9270720,"uniquechannels":27353,"year":2016,"month":"august","language":"241"},{"viewminutes":1029535200,"streamedminutes":11627880,"uniquechannels":29285,"year":2016,"month":"september","language":"241"},{"viewminutes":1162816200,"streamedminutes":10367580,"uniquechannels":29080,"year":2016,"month":"october","language":"241"},{"viewminutes":1011408840,"streamedminutes":9239280,"uniquechannels":32505,"year":2016,"month":"november","language":"241"},{"viewminutes":1111871580,"streamedminutes":12032220,"uniquechannels":11955,"year":2016,"month":"december","language":"241"},{"viewminutes":1142151240,"streamedminutes":12171660,"uniquechannels":39945,"year":2017,"month":"january","language":"241"},{"viewminutes":1232990160,"streamedminutes":11654640,"uniquechannels":37648,"year":2017,"month":"february","language":"241"},{"viewminutes":1078430280,"streamedminutes":8937840,"uniquechannels":30845,"year":2017,"month":"march","language":"241"},{"viewminutes":1010640540,"streamedminutes":8715240,"uniquechannels":29921,"year":2017,"month":"april","language":"241"},{"viewminutes":1120931760,"streamedminutes":16008300,"uniquechannels":37163,"year":2017,"month":"may","language":"241"},{"viewminutes":1138384680,"streamedminutes":15342600,"uniquechannels":36999,"year":2017,"month":"june","language":"241"},{"viewminutes":1187138820,"streamedminutes":15916620,"uniquechannels":38754,"year":2017,"month":"july","language":"241"},{"viewminutes":1218091560,"streamedminutes":15368640,"uniquechannels":36478,"year":2017,"month":"august","language":"241"},{"viewminutes":1199788140,"streamedminutes":14152980,"uniquechannels":33858,"year":2017,"month":"september","language":"241"},{"viewminutes":1394668800,"streamedminutes":15260760,"uniquechannels":35129,"year":2017,"month":"october","language":"241"},{"viewminutes":1223063220,"streamedminutes":14000880,"uniquechannels":32870,"year":2017,"month":"november","language":"241"},{"viewminutes":1266939060,"streamedminutes":14922840,"uniquechannels":37598,"year":2017,"month":"december","language":"241"},{"viewminutes":1245655860,"streamedminutes":15129180,"uniquechannels":40386,"year":2018,"month":"january","language":"241"},{"viewminutes":1040706900,"streamedminutes":14200200,"uniquechannels":35679,"year":2018,"month":"february","language":"241"},{"viewminutes":1160316720,"streamedminutes":14616960,"uniquechannels":38087,"year":2018,"month":"march","language":"241"},{"viewminutes":1255929240,"streamedminutes":16371000,"uniquechannels":35624,"year":2018,"month":"april","language":"241"},{"viewminutes":1340107140,"streamedminutes":16746480,"uniquechannels":36269,"year":2018,"month":"may","language":"241"},{"viewminutes":1421102760,"streamedminutes":17537400,"uniquechannels":39303,"year":2018,"month":"june","language":"241"},{"viewminutes":1460067000,"streamedminutes":17975940,"uniquechannels":40197,"year":2018,"month":"july","language":"241"},{"viewminutes":1591473540,"streamedminutes":19819440,"uniquechannels":42324,"year":2018,"month":"august","language":"241"},{"viewminutes":1337200320,"streamedminutes":19452300,"uniquechannels":41113,"year":2018,"month":"september","language":"241"},{"viewminutes":1358558100,"streamedminutes":18071220,"uniquechannels":37369,"year":2018,"month":"october","language":"241"},{"viewminutes":1234674000,"streamedminutes":15989940,"uniquechannels":35896,"year":2018,"month":"november","language":"241"},{"viewminutes":1453520520,"streamedminutes":19211580,"uniquechannels":38623,"year":2018,"month":"december","language":"241"},{"viewminutes":1506030360,"streamedminutes":19713540,"uniquechannels":40862,"year":2019,"month":"january","language":"241"},{"viewminutes":1293748140,"streamedminutes":18723300,"uniquechannels":44317,"year":2019,"month":"february","language":"241"},{"viewminutes":1451353080,"streamedminutes":22462020,"uniquechannels":45058,"year":2019,"month":"march","language":"241"},{"viewminutes":1439931960,"streamedminutes":21516480,"uniquechannels":42528,"year":2019,"month":"april","language":"241"},{"viewminutes":1646322420,"streamedminutes":21468120,"uniquechannels":40176,"year":2019,"month":"may","language":"241"},{"viewminutes":1550231940,"streamedminutes":21273240,"uniquechannels":40430,"year":2019,"month":"june","language":"241"},{"viewminutes":1500266940,"streamedminutes":22055220,"uniquechannels":40045,"year":2019,"month":"july","language":"241"},{"viewminutes":1528711320,"streamedminutes":23245260,"uniquechannels":42511,"year":2019,"month":"august","language":"241"},{"viewminutes":1361778540,"streamedminutes":22653300,"uniquechannels":39313,"year":2019,"month":"september","language":"241"},{"viewminutes":1344467400,"streamedminutes":18680400,"uniquechannels":35364,"year":2019,"month":"october","language":"241"},{"viewminutes":1332553500,"streamedminutes":18897060,"uniquechannels":36798,"year":2019,"month":"november","language":"241"},{"viewminutes":1427167200,"streamedminutes":21557640,"uniquechannels":37965,"year":2019,"month":"december","language":"241"},{"viewminutes":1432062600,"streamedminutes":20920380,"uniquechannels":37776,"year":2020,"month":"january","language":"241"},{"viewminutes":1633000320,"streamedminutes":24255480,"uniquechannels":39586,"year":2020,"month":"february","language":"241"},{"viewminutes":1619645880,"streamedminutes":25303800,"uniquechannels":41573,"year":2020,"month":"march","language":"241"},{"viewminutes":1802659080,"streamedminutes":21452880,"uniquechannels":37098,"year":2020,"month":"april","language":"241"},{"viewminutes":1800101760,"streamedminutes":21295200,"uniquechannels":36900,"year":2020,"month":"may","language":"241"},{"viewminutes":1733993280,"streamedminutes":20087460,"uniquechannels":37525,"year":2020,"month":"june","language":"241"},{"viewminutes":1908152460,"streamedminutes":21235980,"uniquechannels":38052,"year":2020,"month":"july","language":"241"},{"viewminutes":1917875040,"streamedminutes":20855160,"uniquechannels":38023,"year":2020,"month":"august","language":"241"},{"viewminutes":1830714960,"streamedminutes":19800360,"uniquechannels":35913,"year":2020,"month":"september","language":"241"},{"viewminutes":1902038820,"streamedminutes":20572380,"uniquechannels":38280,"year":2020,"month":"october","language":"241"},{"viewminutes":1702729800,"streamedminutes":18772620,"uniquechannels":35503,"year":2020,"month":"november","language":"241"},{"viewminutes":1652838240,"streamedminutes":19922580,"uniquechannels":37761,"year":2020,"month":"december","language":"241"},{"viewminutes":1818966600,"streamedminutes":21086640,"uniquechannels":39162,"year":2021,"month":"january","language":"241"},{"viewminutes":1785636240,"streamedminutes":19798080,"uniquechannels":37724,"year":2021,"month":"february","language":"241"},{"viewminutes":2009931900,"streamedminutes":22549260,"uniquechannels":40331,"year":2021,"month":"march","language":"241"},{"viewminutes":48176400,"streamedminutes":2129280,"uniquechannels":10949,"year":2016,"month":"january","language":"235"},{"viewminutes":45381960,"streamedminutes":2071860,"uniquechannels":11421,"year":2016,"month":"february","language":"235"},{"viewminutes":47216640,"streamedminutes":2180340,"uniquechannels":11632,"year":2016,"month":"march","language":"235"},{"viewminutes":48430980,"streamedminutes":1940640,"uniquechannels":12381,"year":2016,"month":"april","language":"235"},{"viewminutes":57938820,"streamedminutes":2543520,"uniquechannels":14241,"year":2016,"month":"may","language":"235"},{"viewminutes":48628260,"streamedminutes":1893420,"uniquechannels":12604,"year":2016,"month":"june","language":"235"},{"viewminutes":38980860,"streamedminutes":2355900,"uniquechannels":12537,"year":2016,"month":"july","language":"235"},{"viewminutes":33228300,"streamedminutes":2000280,"uniquechannels":12627,"year":2016,"month":"august","language":"235"},{"viewminutes":31552620,"streamedminutes":2464500,"uniquechannels":12720,"year":2016,"month":"september","language":"235"},{"viewminutes":31829700,"streamedminutes":2329080,"uniquechannels":14019,"year":2016,"month":"october","language":"235"},{"viewminutes":30872160,"streamedminutes":1726440,"uniquechannels":13058,"year":2016,"month":"november","language":"235"},{"viewminutes":40492980,"streamedminutes":2583960,"uniquechannels":4065,"year":2016,"month":"december","language":"235"},{"viewminutes":47341920,"streamedminutes":3086340,"uniquechannels":18477,"year":2017,"month":"january","language":"235"},{"viewminutes":35146860,"streamedminutes":2467740,"uniquechannels":15801,"year":2017,"month":"february","language":"235"},{"viewminutes":33493740,"streamedminutes":1760340,"uniquechannels":13259,"year":2017,"month":"march","language":"235"},{"viewminutes":30987000,"streamedminutes":1873980,"uniquechannels":13509,"year":2017,"month":"april","language":"235"},{"viewminutes":40450320,"streamedminutes":3586440,"uniquechannels":17231,"year":2017,"month":"may","language":"235"},{"viewminutes":40466940,"streamedminutes":3351240,"uniquechannels":16495,"year":2017,"month":"june","language":"235"},{"viewminutes":43689540,"streamedminutes":3557520,"uniquechannels":17794,"year":2017,"month":"july","language":"235"},{"viewminutes":47004540,"streamedminutes":3183060,"uniquechannels":16839,"year":2017,"month":"august","language":"235"},{"viewminutes":32161560,"streamedminutes":2730720,"uniquechannels":15426,"year":2017,"month":"september","language":"235"},{"viewminutes":37081500,"streamedminutes":2945100,"uniquechannels":16175,"year":2017,"month":"october","language":"235"},{"viewminutes":39934980,"streamedminutes":2899860,"uniquechannels":14965,"year":2017,"month":"november","language":"235"},{"viewminutes":36852960,"streamedminutes":3137340,"uniquechannels":16985,"year":2017,"month":"december","language":"235"},{"viewminutes":37212060,"streamedminutes":3785100,"uniquechannels":20487,"year":2018,"month":"january","language":"235"},{"viewminutes":35125740,"streamedminutes":3615660,"uniquechannels":19276,"year":2018,"month":"february","language":"235"},{"viewminutes":48010740,"streamedminutes":4539780,"uniquechannels":23601,"year":2018,"month":"march","language":"235"},{"viewminutes":47943660,"streamedminutes":5827200,"uniquechannels":23414,"year":2018,"month":"april","language":"235"},{"viewminutes":48653760,"streamedminutes":6379980,"uniquechannels":23435,"year":2018,"month":"may","language":"235"},{"viewminutes":52276920,"streamedminutes":5869860,"uniquechannels":23155,"year":2018,"month":"june","language":"235"},{"viewminutes":51596700,"streamedminutes":5913480,"uniquechannels":22249,"year":2018,"month":"july","language":"235"},{"viewminutes":63236580,"streamedminutes":6778800,"uniquechannels":24695,"year":2018,"month":"august","language":"235"},{"viewminutes":49964700,"streamedminutes":5882160,"uniquechannels":22540,"year":2018,"month":"september","language":"235"},{"viewminutes":56658060,"streamedminutes":6086220,"uniquechannels":22809,"year":2018,"month":"october","language":"235"},{"viewminutes":52812240,"streamedminutes":5297400,"uniquechannels":20795,"year":2018,"month":"november","language":"235"},{"viewminutes":57951060,"streamedminutes":6865800,"uniquechannels":24102,"year":2018,"month":"december","language":"235"},{"viewminutes":62057640,"streamedminutes":7017900,"uniquechannels":26521,"year":2019,"month":"january","language":"235"},{"viewminutes":58277700,"streamedminutes":6390780,"uniquechannels":25172,"year":2019,"month":"february","language":"235"},{"viewminutes":63271380,"streamedminutes":6706260,"uniquechannels":24964,"year":2019,"month":"march","language":"235"},{"viewminutes":59130660,"streamedminutes":6507300,"uniquechannels":23610,"year":2019,"month":"april","language":"235"},{"viewminutes":58053000,"streamedminutes":6369180,"uniquechannels":22956,"year":2019,"month":"may","language":"235"},{"viewminutes":58135140,"streamedminutes":5802960,"uniquechannels":21237,"year":2019,"month":"june","language":"235"},{"viewminutes":55603320,"streamedminutes":6298740,"uniquechannels":21786,"year":2019,"month":"july","language":"235"},{"viewminutes":63223620,"streamedminutes":6565020,"uniquechannels":22508,"year":2019,"month":"august","language":"235"},{"viewminutes":54839880,"streamedminutes":5366100,"uniquechannels":19640,"year":2019,"month":"september","language":"235"},{"viewminutes":49089420,"streamedminutes":5241720,"uniquechannels":20021,"year":2019,"month":"october","language":"235"},{"viewminutes":51262020,"streamedminutes":4634820,"uniquechannels":18137,"year":2019,"month":"november","language":"235"},{"viewminutes":55402500,"streamedminutes":5390280,"uniquechannels":20484,"year":2019,"month":"december","language":"235"},{"viewminutes":64029660,"streamedminutes":5321520,"uniquechannels":21340,"year":2020,"month":"january","language":"235"},{"viewminutes":64363140,"streamedminutes":5891580,"uniquechannels":20236,"year":2020,"month":"february","language":"235"},{"viewminutes":85820520,"streamedminutes":7606380,"uniquechannels":26785,"year":2020,"month":"march","language":"235"},{"viewminutes":133402020,"streamedminutes":8215500,"uniquechannels":30553,"year":2020,"month":"april","language":"235"},{"viewminutes":150366840,"streamedminutes":8799120,"uniquechannels":32178,"year":2020,"month":"may","language":"235"},{"viewminutes":127422840,"streamedminutes":7310100,"uniquechannels":27969,"year":2020,"month":"june","language":"235"},{"viewminutes":114318540,"streamedminutes":6769080,"uniquechannels":26361,"year":2020,"month":"july","language":"235"},{"viewminutes":107958660,"streamedminutes":6353760,"uniquechannels":26820,"year":2020,"month":"august","language":"235"},{"viewminutes":101784120,"streamedminutes":5777700,"uniquechannels":24410,"year":2020,"month":"september","language":"235"},{"viewminutes":130150620,"streamedminutes":7050360,"uniquechannels":29538,"year":2020,"month":"october","language":"235"},{"viewminutes":141481860,"streamedminutes":7757520,"uniquechannels":32519,"year":2020,"month":"november","language":"235"},{"viewminutes":166599540,"streamedminutes":8542500,"uniquechannels":35867,"year":2020,"month":"december","language":"235"},{"viewminutes":249230280,"streamedminutes":10312680,"uniquechannels":42553,"year":2021,"month":"january","language":"235"},{"viewminutes":261822420,"streamedminutes":10528560,"uniquechannels":42919,"year":2021,"month":"february","language":"235"},{"viewminutes":255664140,"streamedminutes":10736340,"uniquechannels":42745,"year":2021,"month":"march","language":"235"},{"viewminutes":37251420,"streamedminutes":1552800,"uniquechannels":7376,"year":2016,"month":"january","language":"229"},{"viewminutes":32438040,"streamedminutes":1406040,"uniquechannels":7143,"year":2016,"month":"february","language":"229"},{"viewminutes":41065680,"streamedminutes":1330980,"uniquechannels":7313,"year":2016,"month":"march","language":"229"},{"viewminutes":29421900,"streamedminutes":1042620,"uniquechannels":6649,"year":2016,"month":"april","language":"229"},{"viewminutes":28766700,"streamedminutes":1118580,"uniquechannels":6690,"year":2016,"month":"may","language":"229"},{"viewminutes":48663840,"streamedminutes":892200,"uniquechannels":6401,"year":2016,"month":"june","language":"229"},{"viewminutes":36277500,"streamedminutes":1182060,"uniquechannels":7015,"year":2016,"month":"july","language":"229"},{"viewminutes":31557180,"streamedminutes":1145160,"uniquechannels":7160,"year":2016,"month":"august","language":"229"},{"viewminutes":30250740,"streamedminutes":1651020,"uniquechannels":7944,"year":2016,"month":"september","language":"229"},{"viewminutes":36796620,"streamedminutes":1527780,"uniquechannels":8817,"year":2016,"month":"october","language":"229"},{"viewminutes":35223540,"streamedminutes":1240860,"uniquechannels":8856,"year":2016,"month":"november","language":"229"},{"viewminutes":39094260,"streamedminutes":1660080,"uniquechannels":3176,"year":2016,"month":"december","language":"229"},{"viewminutes":40646280,"streamedminutes":1858200,"uniquechannels":11232,"year":2017,"month":"january","language":"229"},{"viewminutes":35882760,"streamedminutes":1599540,"uniquechannels":10074,"year":2017,"month":"february","language":"229"},{"viewminutes":42407460,"streamedminutes":1321260,"uniquechannels":9143,"year":2017,"month":"march","language":"229"},{"viewminutes":30572760,"streamedminutes":1222740,"uniquechannels":8671,"year":2017,"month":"april","language":"229"},{"viewminutes":39644520,"streamedminutes":2225700,"uniquechannels":9974,"year":2017,"month":"may","language":"229"},{"viewminutes":37430640,"streamedminutes":2182200,"uniquechannels":10246,"year":2017,"month":"june","language":"229"},{"viewminutes":43261500,"streamedminutes":2347080,"uniquechannels":10818,"year":2017,"month":"july","language":"229"},{"viewminutes":41976240,"streamedminutes":2258940,"uniquechannels":10802,"year":2017,"month":"august","language":"229"},{"viewminutes":38931420,"streamedminutes":2299680,"uniquechannels":11272,"year":2017,"month":"september","language":"229"},{"viewminutes":42082740,"streamedminutes":2322000,"uniquechannels":12116,"year":2017,"month":"october","language":"229"},{"viewminutes":49130160,"streamedminutes":2419620,"uniquechannels":11273,"year":2017,"month":"november","language":"229"},{"viewminutes":49066200,"streamedminutes":2638740,"uniquechannels":13483,"year":2017,"month":"december","language":"229"},{"viewminutes":57724920,"streamedminutes":3137640,"uniquechannels":14612,"year":2018,"month":"january","language":"229"},{"viewminutes":50926320,"streamedminutes":3020280,"uniquechannels":14524,"year":2018,"month":"february","language":"229"},{"viewminutes":56456100,"streamedminutes":3402660,"uniquechannels":16546,"year":2018,"month":"march","language":"229"},{"viewminutes":59796600,"streamedminutes":3762840,"uniquechannels":15035,"year":2018,"month":"april","language":"229"},{"viewminutes":54709320,"streamedminutes":3532380,"uniquechannels":13613,"year":2018,"month":"may","language":"229"},{"viewminutes":64977180,"streamedminutes":3499860,"uniquechannels":14591,"year":2018,"month":"june","language":"229"},{"viewminutes":64989600,"streamedminutes":3523560,"uniquechannels":14088,"year":2018,"month":"july","language":"229"},{"viewminutes":71761200,"streamedminutes":3924480,"uniquechannels":15222,"year":2018,"month":"august","language":"229"},{"viewminutes":64159920,"streamedminutes":3863880,"uniquechannels":14983,"year":2018,"month":"september","language":"229"},{"viewminutes":68308920,"streamedminutes":4018500,"uniquechannels":15746,"year":2018,"month":"october","language":"229"},{"viewminutes":71192640,"streamedminutes":3857100,"uniquechannels":15727,"year":2018,"month":"november","language":"229"},{"viewminutes":77099100,"streamedminutes":4565880,"uniquechannels":18274,"year":2018,"month":"december","language":"229"},{"viewminutes":90077760,"streamedminutes":4740000,"uniquechannels":18131,"year":2019,"month":"january","language":"229"},{"viewminutes":82267740,"streamedminutes":4372020,"uniquechannels":17228,"year":2019,"month":"february","language":"229"},{"viewminutes":95780220,"streamedminutes":4520940,"uniquechannels":17125,"year":2019,"month":"march","language":"229"},{"viewminutes":79438620,"streamedminutes":3821040,"uniquechannels":14471,"year":2019,"month":"april","language":"229"},{"viewminutes":92912820,"streamedminutes":3771600,"uniquechannels":13846,"year":2019,"month":"may","language":"229"},{"viewminutes":83704980,"streamedminutes":3539040,"uniquechannels":13630,"year":2019,"month":"june","language":"229"},{"viewminutes":97227480,"streamedminutes":3937140,"uniquechannels":13767,"year":2019,"month":"july","language":"229"},{"viewminutes":111912540,"streamedminutes":4135020,"uniquechannels":14673,"year":2019,"month":"august","language":"229"},{"viewminutes":100846620,"streamedminutes":4274820,"uniquechannels":14264,"year":2019,"month":"september","language":"229"},{"viewminutes":82585980,"streamedminutes":4013520,"uniquechannels":15116,"year":2019,"month":"october","language":"229"},{"viewminutes":96448320,"streamedminutes":4142460,"uniquechannels":15198,"year":2019,"month":"november","language":"229"},{"viewminutes":109884060,"streamedminutes":4340160,"uniquechannels":15952,"year":2019,"month":"december","language":"229"},{"viewminutes":148551540,"streamedminutes":4555140,"uniquechannels":16459,"year":2020,"month":"january","language":"229"},{"viewminutes":152225700,"streamedminutes":5205720,"uniquechannels":15749,"year":2020,"month":"february","language":"229"},{"viewminutes":163050480,"streamedminutes":6091320,"uniquechannels":18671,"year":2020,"month":"march","language":"229"},{"viewminutes":237955860,"streamedminutes":5986140,"uniquechannels":20000,"year":2020,"month":"april","language":"229"},{"viewminutes":228106500,"streamedminutes":5486760,"uniquechannels":17735,"year":2020,"month":"may","language":"229"},{"viewminutes":164023260,"streamedminutes":3718680,"uniquechannels":12824,"year":2020,"month":"june","language":"229"},{"viewminutes":152818680,"streamedminutes":4326420,"uniquechannels":13863,"year":2020,"month":"july","language":"229"},{"viewminutes":155842740,"streamedminutes":4203420,"uniquechannels":13889,"year":2020,"month":"august","language":"229"},{"viewminutes":172444200,"streamedminutes":4437900,"uniquechannels":14492,"year":2020,"month":"september","language":"229"},{"viewminutes":210306660,"streamedminutes":5130600,"uniquechannels":16977,"year":2020,"month":"october","language":"229"},{"viewminutes":208617180,"streamedminutes":5021040,"uniquechannels":16069,"year":2020,"month":"november","language":"229"},{"viewminutes":188329860,"streamedminutes":5165100,"uniquechannels":16707,"year":2020,"month":"december","language":"229"},{"viewminutes":225244500,"streamedminutes":5901900,"uniquechannels":17399,"year":2021,"month":"january","language":"229"},{"viewminutes":224023500,"streamedminutes":5651760,"uniquechannels":16779,"year":2021,"month":"february","language":"229"},{"viewminutes":289637100,"streamedminutes":6421260,"uniquechannels":18801,"year":2021,"month":"march","language":"229"},{"viewminutes":80970900,"streamedminutes":1918320,"uniquechannels":9252,"year":2016,"month":"january","language":"226"},{"viewminutes":75699720,"streamedminutes":1942440,"uniquechannels":10209,"year":2016,"month":"february","language":"226"},{"viewminutes":103736040,"streamedminutes":2541420,"uniquechannels":11053,"year":2016,"month":"march","language":"226"},{"viewminutes":100003440,"streamedminutes":2125020,"uniquechannels":10301,"year":2016,"month":"april","language":"226"},{"viewminutes":129322200,"streamedminutes":2781060,"uniquechannels":12669,"year":2016,"month":"may","language":"226"},{"viewminutes":131952720,"streamedminutes":2089140,"uniquechannels":11316,"year":2016,"month":"june","language":"226"},{"viewminutes":146208120,"streamedminutes":2935440,"uniquechannels":12362,"year":2016,"month":"july","language":"226"},{"viewminutes":163886160,"streamedminutes":2858880,"uniquechannels":13250,"year":2016,"month":"august","language":"226"},{"viewminutes":145702980,"streamedminutes":3872220,"uniquechannels":14072,"year":2016,"month":"september","language":"226"},{"viewminutes":149812320,"streamedminutes":3584640,"uniquechannels":15228,"year":2016,"month":"october","language":"226"},{"viewminutes":132470580,"streamedminutes":3123240,"uniquechannels":16447,"year":2016,"month":"november","language":"226"},{"viewminutes":188759400,"streamedminutes":4164660,"uniquechannels":5707,"year":2016,"month":"december","language":"226"},{"viewminutes":204802500,"streamedminutes":3831840,"uniquechannels":16503,"year":2017,"month":"january","language":"226"},{"viewminutes":191970720,"streamedminutes":3717600,"uniquechannels":17515,"year":2017,"month":"february","language":"226"},{"viewminutes":227312040,"streamedminutes":3130320,"uniquechannels":17070,"year":2017,"month":"march","language":"226"},{"viewminutes":194836080,"streamedminutes":2966940,"uniquechannels":15507,"year":2017,"month":"april","language":"226"},{"viewminutes":310895760,"streamedminutes":6204180,"uniquechannels":20518,"year":2017,"month":"may","language":"226"},{"viewminutes":275515320,"streamedminutes":6156000,"uniquechannels":20054,"year":2017,"month":"june","language":"226"},{"viewminutes":332207340,"streamedminutes":6359520,"uniquechannels":20883,"year":2017,"month":"july","language":"226"},{"viewminutes":345564420,"streamedminutes":6378000,"uniquechannels":20376,"year":2017,"month":"august","language":"226"},{"viewminutes":347636580,"streamedminutes":6764640,"uniquechannels":22496,"year":2017,"month":"september","language":"226"},{"viewminutes":458001660,"streamedminutes":6899160,"uniquechannels":22885,"year":2017,"month":"october","language":"226"},{"viewminutes":346832100,"streamedminutes":6612300,"uniquechannels":22120,"year":2017,"month":"november","language":"226"},{"viewminutes":384844080,"streamedminutes":7643040,"uniquechannels":28211,"year":2017,"month":"december","language":"226"},{"viewminutes":425626800,"streamedminutes":9113400,"uniquechannels":30765,"year":2018,"month":"january","language":"226"},{"viewminutes":391027140,"streamedminutes":8711460,"uniquechannels":27979,"year":2018,"month":"february","language":"226"},{"viewminutes":447845040,"streamedminutes":10001580,"uniquechannels":33021,"year":2018,"month":"march","language":"226"},{"viewminutes":467889720,"streamedminutes":11647740,"uniquechannels":30365,"year":2018,"month":"april","language":"226"},{"viewminutes":540134100,"streamedminutes":13264380,"uniquechannels":33993,"year":2018,"month":"may","language":"226"},{"viewminutes":497523240,"streamedminutes":13674420,"uniquechannels":35372,"year":2018,"month":"june","language":"226"},{"viewminutes":511639620,"streamedminutes":13861920,"uniquechannels":35670,"year":2018,"month":"july","language":"226"},{"viewminutes":590159340,"streamedminutes":14908740,"uniquechannels":37184,"year":2018,"month":"august","language":"226"},{"viewminutes":513300120,"streamedminutes":15775620,"uniquechannels":37759,"year":2018,"month":"september","language":"226"},{"viewminutes":575801520,"streamedminutes":15554880,"uniquechannels":37452,"year":2018,"month":"october","language":"226"},{"viewminutes":527231940,"streamedminutes":14245320,"uniquechannels":36563,"year":2018,"month":"november","language":"226"},{"viewminutes":603457260,"streamedminutes":16344780,"uniquechannels":38220,"year":2018,"month":"december","language":"226"},{"viewminutes":601066440,"streamedminutes":16101660,"uniquechannels":38315,"year":2019,"month":"january","language":"226"},{"viewminutes":606016500,"streamedminutes":16810860,"uniquechannels":40703,"year":2019,"month":"february","language":"226"},{"viewminutes":661947180,"streamedminutes":19484760,"uniquechannels":42509,"year":2019,"month":"march","language":"226"},{"viewminutes":606847740,"streamedminutes":18206220,"uniquechannels":40600,"year":2019,"month":"april","language":"226"},{"viewminutes":668549400,"streamedminutes":18853440,"uniquechannels":41887,"year":2019,"month":"may","language":"226"},{"viewminutes":630764760,"streamedminutes":17868660,"uniquechannels":41642,"year":2019,"month":"june","language":"226"},{"viewminutes":626263620,"streamedminutes":17585040,"uniquechannels":38625,"year":2019,"month":"july","language":"226"},{"viewminutes":688248960,"streamedminutes":18280860,"uniquechannels":40108,"year":2019,"month":"august","language":"226"},{"viewminutes":654186420,"streamedminutes":18628080,"uniquechannels":42067,"year":2019,"month":"september","language":"226"},{"viewminutes":655366200,"streamedminutes":17344680,"uniquechannels":39584,"year":2019,"month":"october","language":"226"},{"viewminutes":647812860,"streamedminutes":18195480,"uniquechannels":39248,"year":2019,"month":"november","language":"226"},{"viewminutes":687089580,"streamedminutes":18918840,"uniquechannels":40548,"year":2019,"month":"december","language":"226"},{"viewminutes":773459940,"streamedminutes":19441920,"uniquechannels":41340,"year":2020,"month":"january","language":"226"},{"viewminutes":902905140,"streamedminutes":22050900,"uniquechannels":41657,"year":2020,"month":"february","language":"226"},{"viewminutes":887587740,"streamedminutes":22537380,"uniquechannels":46333,"year":2020,"month":"march","language":"226"},{"viewminutes":987742740,"streamedminutes":21101820,"uniquechannels":49506,"year":2020,"month":"april","language":"226"},{"viewminutes":1268245140,"streamedminutes":24568920,"uniquechannels":55475,"year":2020,"month":"may","language":"226"},{"viewminutes":1156290120,"streamedminutes":21345060,"uniquechannels":51569,"year":2020,"month":"june","language":"226"},{"viewminutes":1160938800,"streamedminutes":23434500,"uniquechannels":56117,"year":2020,"month":"july","language":"226"},{"viewminutes":1332757920,"streamedminutes":23897820,"uniquechannels":58662,"year":2020,"month":"august","language":"226"},{"viewminutes":1241990880,"streamedminutes":24910680,"uniquechannels":62554,"year":2020,"month":"september","language":"226"},{"viewminutes":1248195660,"streamedminutes":26292420,"uniquechannels":61703,"year":2020,"month":"october","language":"226"},{"viewminutes":1288807800,"streamedminutes":26021700,"uniquechannels":61715,"year":2020,"month":"november","language":"226"},{"viewminutes":1455698460,"streamedminutes":27859320,"uniquechannels":67179,"year":2020,"month":"december","language":"226"},{"viewminutes":1824104520,"streamedminutes":30346500,"uniquechannels":71942,"year":2021,"month":"january","language":"226"},{"viewminutes":1726927800,"streamedminutes":31187820,"uniquechannels":70803,"year":2021,"month":"february","language":"226"},{"viewminutes":1893400620,"streamedminutes":32513820,"uniquechannels":75267,"year":2021,"month":"march","language":"226"},{"viewminutes":228079320,"streamedminutes":1047300,"uniquechannels":2948,"year":2016,"month":"january","language":"231"},{"viewminutes":206441940,"streamedminutes":1088640,"uniquechannels":3103,"year":2016,"month":"february","language":"231"},{"viewminutes":239015940,"streamedminutes":1156020,"uniquechannels":3273,"year":2016,"month":"march","language":"231"},{"viewminutes":188999700,"streamedminutes":1019040,"uniquechannels":3242,"year":2016,"month":"april","language":"231"},{"viewminutes":210096000,"streamedminutes":1215120,"uniquechannels":3680,"year":2016,"month":"may","language":"231"},{"viewminutes":167593200,"streamedminutes":999480,"uniquechannels":3130,"year":2016,"month":"june","language":"231"},{"viewminutes":175476120,"streamedminutes":1332600,"uniquechannels":3817,"year":2016,"month":"july","language":"231"},{"viewminutes":214491300,"streamedminutes":1536300,"uniquechannels":4720,"year":2016,"month":"august","language":"231"},{"viewminutes":266807460,"streamedminutes":2546640,"uniquechannels":5947,"year":2016,"month":"september","language":"231"},{"viewminutes":455640180,"streamedminutes":3063540,"uniquechannels":10237,"year":2016,"month":"october","language":"231"},{"viewminutes":878506740,"streamedminutes":6235140,"uniquechannels":21385,"year":2016,"month":"november","language":"231"},{"viewminutes":948520140,"streamedminutes":8259660,"uniquechannels":6951,"year":2016,"month":"december","language":"231"},{"viewminutes":1096071300,"streamedminutes":9097500,"uniquechannels":25019,"year":2017,"month":"january","language":"231"},{"viewminutes":1508889300,"streamedminutes":9605880,"uniquechannels":27986,"year":2017,"month":"february","language":"231"},{"viewminutes":1498382760,"streamedminutes":8926860,"uniquechannels":26682,"year":2017,"month":"march","language":"231"},{"viewminutes":1383274080,"streamedminutes":8932920,"uniquechannels":25867,"year":2017,"month":"april","language":"231"},{"viewminutes":1634831160,"streamedminutes":16169220,"uniquechannels":33410,"year":2017,"month":"may","language":"231"},{"viewminutes":1780412400,"streamedminutes":17485920,"uniquechannels":36111,"year":2017,"month":"june","language":"231"},{"viewminutes":1755963960,"streamedminutes":17379000,"uniquechannels":36744,"year":2017,"month":"july","language":"231"},{"viewminutes":1868155920,"streamedminutes":17406600,"uniquechannels":35772,"year":2017,"month":"august","language":"231"},{"viewminutes":1834864080,"streamedminutes":17536200,"uniquechannels":36574,"year":2017,"month":"september","language":"231"},{"viewminutes":2177609880,"streamedminutes":18624360,"uniquechannels":40296,"year":2017,"month":"october","language":"231"},{"viewminutes":2223376500,"streamedminutes":19184580,"uniquechannels":45362,"year":2017,"month":"november","language":"231"},{"viewminutes":2328430620,"streamedminutes":21684360,"uniquechannels":52910,"year":2017,"month":"december","language":"231"},{"viewminutes":2703323760,"streamedminutes":27049860,"uniquechannels":64923,"year":2018,"month":"january","language":"231"},{"viewminutes":2363124120,"streamedminutes":24966000,"uniquechannels":59053,"year":2018,"month":"february","language":"231"},{"viewminutes":2470944300,"streamedminutes":26767500,"uniquechannels":62126,"year":2018,"month":"march","language":"231"},{"viewminutes":2483878080,"streamedminutes":30616980,"uniquechannels":59752,"year":2018,"month":"april","language":"231"},{"viewminutes":2599296000,"streamedminutes":35816580,"uniquechannels":65114,"year":2018,"month":"may","language":"231"},{"viewminutes":2625996360,"streamedminutes":35602260,"uniquechannels":67761,"year":2018,"month":"june","language":"231"},{"viewminutes":2850343260,"streamedminutes":37960080,"uniquechannels":73032,"year":2018,"month":"july","language":"231"},{"viewminutes":2902963260,"streamedminutes":41926320,"uniquechannels":75940,"year":2018,"month":"august","language":"231"},{"viewminutes":2632292820,"streamedminutes":40116900,"uniquechannels":77532,"year":2018,"month":"september","language":"231"},{"viewminutes":3403469820,"streamedminutes":43943460,"uniquechannels":84200,"year":2018,"month":"october","language":"231"},{"viewminutes":2780881260,"streamedminutes":42967920,"uniquechannels":84754,"year":2018,"month":"november","language":"231"},{"viewminutes":3185925360,"streamedminutes":50410980,"uniquechannels":95009,"year":2018,"month":"december","language":"231"},{"viewminutes":3566102520,"streamedminutes":55576080,"uniquechannels":107364,"year":2019,"month":"january","language":"231"},{"viewminutes":3365907660,"streamedminutes":52323900,"uniquechannels":110781,"year":2019,"month":"february","language":"231"},{"viewminutes":3695642280,"streamedminutes":59543340,"uniquechannels":116048,"year":2019,"month":"march","language":"231"},{"viewminutes":3340520220,"streamedminutes":56150340,"uniquechannels":106034,"year":2019,"month":"april","language":"231"},{"viewminutes":3498480720,"streamedminutes":58976040,"uniquechannels":109445,"year":2019,"month":"may","language":"231"},{"viewminutes":3628511940,"streamedminutes":57874440,"uniquechannels":108449,"year":2019,"month":"june","language":"231"},{"viewminutes":3490553700,"streamedminutes":61907940,"uniquechannels":113540,"year":2019,"month":"july","language":"231"},{"viewminutes":3756704700,"streamedminutes":63170040,"uniquechannels":122329,"year":2019,"month":"august","language":"231"},{"viewminutes":3447983580,"streamedminutes":63001740,"uniquechannels":120534,"year":2019,"month":"september","language":"231"},{"viewminutes":3493433220,"streamedminutes":61655880,"uniquechannels":121998,"year":2019,"month":"october","language":"231"},{"viewminutes":3382888680,"streamedminutes":63197100,"uniquechannels":125907,"year":2019,"month":"november","language":"231"},{"viewminutes":3717687600,"streamedminutes":72046860,"uniquechannels":138421,"year":2019,"month":"december","language":"231"},{"viewminutes":3745128180,"streamedminutes":76446240,"uniquechannels":144413,"year":2020,"month":"january","language":"231"},{"viewminutes":4261624080,"streamedminutes":84379080,"uniquechannels":147385,"year":2020,"month":"february","language":"231"},{"viewminutes":4580093340,"streamedminutes":91978380,"uniquechannels":165759,"year":2020,"month":"march","language":"231"},{"viewminutes":4917465360,"streamedminutes":76829760,"uniquechannels":146599,"year":2020,"month":"april","language":"231"},{"viewminutes":5023965960,"streamedminutes":79844640,"uniquechannels":151681,"year":2020,"month":"may","language":"231"},{"viewminutes":4767797280,"streamedminutes":72229680,"uniquechannels":143720,"year":2020,"month":"june","language":"231"},{"viewminutes":5047310460,"streamedminutes":75200940,"uniquechannels":146047,"year":2020,"month":"july","language":"231"},{"viewminutes":5231706180,"streamedminutes":76990800,"uniquechannels":156808,"year":2020,"month":"august","language":"231"},{"viewminutes":5212731900,"streamedminutes":83253720,"uniquechannels":164628,"year":2020,"month":"september","language":"231"},{"viewminutes":5543350560,"streamedminutes":80546280,"uniquechannels":154923,"year":2020,"month":"october","language":"231"},{"viewminutes":4895238240,"streamedminutes":75378000,"uniquechannels":148818,"year":2020,"month":"november","language":"231"},{"viewminutes":5501434080,"streamedminutes":88147980,"uniquechannels":174313,"year":2020,"month":"december","language":"231"},{"viewminutes":6445209660,"streamedminutes":94513260,"uniquechannels":178245,"year":2021,"month":"january","language":"231"},{"viewminutes":5840247960,"streamedminutes":83735700,"uniquechannels":155599,"year":2021,"month":"february","language":"231"},{"viewminutes":5683509840,"streamedminutes":83765160,"uniquechannels":148087,"year":2021,"month":"march","language":"231"},{"viewminutes":16805326200,"streamedminutes":198202980,"uniquechannels":994743,"year":2016,"month":"january","language":"217"},{"viewminutes":14862261060,"streamedminutes":177400500,"uniquechannels":959655,"year":2016,"month":"february","language":"217"},{"viewminutes":16692525720,"streamedminutes":186276360,"uniquechannels":1019182,"year":2016,"month":"march","language":"217"},{"viewminutes":15781129560,"streamedminutes":163733640,"uniquechannels":1006323,"year":2016,"month":"april","language":"217"},{"viewminutes":15004468680,"streamedminutes":200600400,"uniquechannels":1131856,"year":2016,"month":"may","language":"217"},{"viewminutes":14859179640,"streamedminutes":162260280,"uniquechannels":1090040,"year":2016,"month":"june","language":"217"},{"viewminutes":15220896300,"streamedminutes":203536320,"uniquechannels":1173268,"year":2016,"month":"july","language":"217"},{"viewminutes":14434433880,"streamedminutes":185997900,"uniquechannels":1175985,"year":2016,"month":"august","language":"217"},{"viewminutes":13385210640,"streamedminutes":214037220,"uniquechannels":1111997,"year":2016,"month":"september","language":"217"},{"viewminutes":15227894520,"streamedminutes":203416560,"uniquechannels":1167418,"year":2016,"month":"october","language":"217"},{"viewminutes":13944346860,"streamedminutes":174624420,"uniquechannels":1173786,"year":2016,"month":"november","language":"217"},{"viewminutes":15555067740,"streamedminutes":237292020,"uniquechannels":355829,"year":2016,"month":"december","language":"217"},{"viewminutes":19569359100,"streamedminutes":273911160,"uniquechannels":1580905,"year":2017,"month":"january","language":"217"},{"viewminutes":15453709620,"streamedminutes":227217480,"uniquechannels":1351745,"year":2017,"month":"february","language":"217"},{"viewminutes":15835512240,"streamedminutes":164854380,"uniquechannels":1144190,"year":2017,"month":"march","language":"217"},{"viewminutes":15177622980,"streamedminutes":164937900,"uniquechannels":1081237,"year":2017,"month":"april","language":"217"},{"viewminutes":16236908940,"streamedminutes":342786960,"uniquechannels":1528454,"year":2017,"month":"may","language":"217"},{"viewminutes":16165919100,"streamedminutes":347804100,"uniquechannels":1577056,"year":2017,"month":"june","language":"217"},{"viewminutes":18537460020,"streamedminutes":380295000,"uniquechannels":1704761,"year":2017,"month":"july","language":"217"},{"viewminutes":16978795560,"streamedminutes":353207580,"uniquechannels":1626350,"year":2017,"month":"august","language":"217"},{"viewminutes":16826599080,"streamedminutes":357279480,"uniquechannels":1535336,"year":2017,"month":"september","language":"217"},{"viewminutes":18750655080,"streamedminutes":392048280,"uniquechannels":1654810,"year":2017,"month":"october","language":"217"},{"viewminutes":18410176080,"streamedminutes":393690180,"uniquechannels":1642345,"year":2017,"month":"november","language":"217"},{"viewminutes":17890664400,"streamedminutes":419568780,"uniquechannels":1799639,"year":2017,"month":"december","language":"217"},{"viewminutes":23686290300,"streamedminutes":483820980,"uniquechannels":2127252,"year":2018,"month":"january","language":"217"},{"viewminutes":19490737080,"streamedminutes":499805340,"uniquechannels":2067931,"year":2018,"month":"february","language":"217"},{"viewminutes":23653393920,"streamedminutes":604891380,"uniquechannels":2571388,"year":2018,"month":"march","language":"217"},{"viewminutes":24512140140,"streamedminutes":737836980,"uniquechannels":2652404,"year":2018,"month":"april","language":"217"},{"viewminutes":24892840200,"streamedminutes":801416460,"uniquechannels":2706078,"year":2018,"month":"may","language":"217"},{"viewminutes":26416083780,"streamedminutes":783078540,"uniquechannels":2755504,"year":2018,"month":"june","language":"217"},{"viewminutes":26453732040,"streamedminutes":821913720,"uniquechannels":2851122,"year":2018,"month":"july","language":"217"},{"viewminutes":28285817460,"streamedminutes":856926960,"uniquechannels":3032121,"year":2018,"month":"august","language":"217"},{"viewminutes":27579643980,"streamedminutes":823700820,"uniquechannels":2865547,"year":2018,"month":"september","language":"217"},{"viewminutes":27474996240,"streamedminutes":840329940,"uniquechannels":2869343,"year":2018,"month":"october","language":"217"},{"viewminutes":25095976320,"streamedminutes":770397600,"uniquechannels":2803870,"year":2018,"month":"november","language":"217"},{"viewminutes":27441730980,"streamedminutes":903344700,"uniquechannels":3105277,"year":2018,"month":"december","language":"217"},{"viewminutes":30091002120,"streamedminutes":927062220,"uniquechannels":3277612,"year":2019,"month":"january","language":"217"},{"viewminutes":28372218720,"streamedminutes":844805700,"uniquechannels":3109534,"year":2019,"month":"february","language":"217"},{"viewminutes":30730595460,"streamedminutes":914668800,"uniquechannels":3240556,"year":2019,"month":"march","language":"217"},{"viewminutes":28308146820,"streamedminutes":870580320,"uniquechannels":3116009,"year":2019,"month":"april","language":"217"},{"viewminutes":29579411580,"streamedminutes":868113660,"uniquechannels":3047652,"year":2019,"month":"may","language":"217"},{"viewminutes":29424917760,"streamedminutes":848674620,"uniquechannels":2876427,"year":2019,"month":"june","language":"217"},{"viewminutes":28907900880,"streamedminutes":875260140,"uniquechannels":2783544,"year":2019,"month":"july","language":"217"},{"viewminutes":31362341400,"streamedminutes":851663940,"uniquechannels":2698189,"year":2019,"month":"august","language":"217"},{"viewminutes":26546776620,"streamedminutes":780871260,"uniquechannels":2382720,"year":2019,"month":"september","language":"217"},{"viewminutes":25299353880,"streamedminutes":731417940,"uniquechannels":2307469,"year":2019,"month":"october","language":"217"},{"viewminutes":24547690740,"streamedminutes":707997720,"uniquechannels":2283530,"year":2019,"month":"november","language":"217"},{"viewminutes":26110304820,"streamedminutes":786292620,"uniquechannels":2547013,"year":2019,"month":"december","language":"217"},{"viewminutes":30305220360,"streamedminutes":834472020,"uniquechannels":2801262,"year":2020,"month":"january","language":"217"},{"viewminutes":29227888980,"streamedminutes":817343400,"uniquechannels":2459853,"year":2020,"month":"february","language":"217"},{"viewminutes":33124415280,"streamedminutes":1011417420,"uniquechannels":3268166,"year":2020,"month":"march","language":"217"},{"viewminutes":50351026380,"streamedminutes":978556920,"uniquechannels":3490862,"year":2020,"month":"april","language":"217"},{"viewminutes":45860783040,"streamedminutes":1067651940,"uniquechannels":3775970,"year":2020,"month":"may","language":"217"},{"viewminutes":44160342780,"streamedminutes":966096600,"uniquechannels":3485601,"year":2020,"month":"june","language":"217"},{"viewminutes":43409624700,"streamedminutes":1080115260,"uniquechannels":3800933,"year":2020,"month":"july","language":"217"},{"viewminutes":44401998120,"streamedminutes":1056504420,"uniquechannels":3989069,"year":2020,"month":"august","language":"217"},{"viewminutes":44542540320,"streamedminutes":1038197580,"uniquechannels":3880047,"year":2020,"month":"september","language":"217"},{"viewminutes":48425934000,"streamedminutes":1142782800,"uniquechannels":4293582,"year":2020,"month":"october","language":"217"},{"viewminutes":48938248380,"streamedminutes":1120214880,"uniquechannels":4306973,"year":2020,"month":"november","language":"217"},{"viewminutes":51986576880,"streamedminutes":1195355400,"uniquechannels":4520938,"year":2020,"month":"december","language":"217"},{"viewminutes":59758148760,"streamedminutes":1367880480,"uniquechannels":5078208,"year":2021,"month":"january","language":"217"},{"viewminutes":55365211320,"streamedminutes":1294883220,"uniquechannels":4747244,"year":2021,"month":"february","language":"217"},{"viewminutes":61580335500,"streamedminutes":1375285800,"uniquechannels":4844026,"year":2021,"month":"march","language":"217"},{"viewminutes":1115149920,"streamedminutes":16585200,"uniquechannels":75089,"year":2016,"month":"january","language":"214"},{"viewminutes":1163400720,"streamedminutes":16670580,"uniquechannels":82266,"year":2016,"month":"february","language":"214"},{"viewminutes":1099731600,"streamedminutes":16206120,"uniquechannels":79992,"year":2016,"month":"march","language":"214"},{"viewminutes":1110148800,"streamedminutes":14821260,"uniquechannels":84205,"year":2016,"month":"april","language":"214"},{"viewminutes":1215300240,"streamedminutes":17372160,"uniquechannels":88378,"year":2016,"month":"may","language":"214"},{"viewminutes":1100547540,"streamedminutes":13856160,"uniquechannels":81995,"year":2016,"month":"june","language":"214"},{"viewminutes":1097056260,"streamedminutes":17272680,"uniquechannels":85387,"year":2016,"month":"july","language":"214"},{"viewminutes":1163977380,"streamedminutes":15709200,"uniquechannels":86680,"year":2016,"month":"august","language":"214"},{"viewminutes":1091895420,"streamedminutes":18137640,"uniquechannels":84384,"year":2016,"month":"september","language":"214"},{"viewminutes":1311316140,"streamedminutes":17588220,"uniquechannels":91832,"year":2016,"month":"october","language":"214"},{"viewminutes":1183047060,"streamedminutes":14616300,"uniquechannels":91361,"year":2016,"month":"november","language":"214"},{"viewminutes":1232940600,"streamedminutes":19609740,"uniquechannels":27928,"year":2016,"month":"december","language":"214"},{"viewminutes":1478116380,"streamedminutes":22116360,"uniquechannels":115857,"year":2017,"month":"january","language":"214"},{"viewminutes":1315713240,"streamedminutes":19686360,"uniquechannels":108967,"year":2017,"month":"february","language":"214"},{"viewminutes":1335849420,"streamedminutes":14857740,"uniquechannels":90322,"year":2017,"month":"march","language":"214"},{"viewminutes":1348537500,"streamedminutes":13954500,"uniquechannels":85853,"year":2017,"month":"april","language":"214"},{"viewminutes":1490619720,"streamedminutes":26138280,"uniquechannels":109633,"year":2017,"month":"may","language":"214"},{"viewminutes":1384497000,"streamedminutes":26064120,"uniquechannels":109745,"year":2017,"month":"june","language":"214"},{"viewminutes":1455152760,"streamedminutes":27297780,"uniquechannels":113069,"year":2017,"month":"july","language":"214"},{"viewminutes":1245101940,"streamedminutes":25052160,"uniquechannels":108307,"year":2017,"month":"august","language":"214"},{"viewminutes":1324381380,"streamedminutes":23086620,"uniquechannels":102971,"year":2017,"month":"september","language":"214"},{"viewminutes":1415381460,"streamedminutes":25777140,"uniquechannels":111832,"year":2017,"month":"october","language":"214"},{"viewminutes":1252272900,"streamedminutes":24350760,"uniquechannels":103052,"year":2017,"month":"november","language":"214"},{"viewminutes":1239584520,"streamedminutes":25204320,"uniquechannels":114493,"year":2017,"month":"december","language":"214"},{"viewminutes":1671063840,"streamedminutes":30868380,"uniquechannels":136294,"year":2018,"month":"january","language":"214"},{"viewminutes":1550263380,"streamedminutes":29477640,"uniquechannels":128603,"year":2018,"month":"february","language":"214"},{"viewminutes":1977613200,"streamedminutes":33749700,"uniquechannels":149332,"year":2018,"month":"march","language":"214"},{"viewminutes":1878274560,"streamedminutes":40587120,"uniquechannels":150717,"year":2018,"month":"april","language":"214"},{"viewminutes":2154317340,"streamedminutes":43625820,"uniquechannels":152686,"year":2018,"month":"may","language":"214"},{"viewminutes":2018537340,"streamedminutes":39937560,"uniquechannels":148647,"year":2018,"month":"june","language":"214"},{"viewminutes":1761852720,"streamedminutes":37679640,"uniquechannels":139750,"year":2018,"month":"july","language":"214"},{"viewminutes":2077181460,"streamedminutes":44559660,"uniquechannels":155811,"year":2018,"month":"august","language":"214"},{"viewminutes":1961822520,"streamedminutes":43174200,"uniquechannels":150270,"year":2018,"month":"september","language":"214"},{"viewminutes":2263097160,"streamedminutes":46865280,"uniquechannels":159041,"year":2018,"month":"october","language":"214"},{"viewminutes":2361830460,"streamedminutes":45066960,"uniquechannels":162285,"year":2018,"month":"november","language":"214"},{"viewminutes":2047773840,"streamedminutes":50553300,"uniquechannels":171489,"year":2018,"month":"december","language":"214"},{"viewminutes":2463283140,"streamedminutes":53848080,"uniquechannels":183169,"year":2019,"month":"january","language":"214"},{"viewminutes":2373885180,"streamedminutes":50524260,"uniquechannels":180335,"year":2019,"month":"february","language":"214"},{"viewminutes":2631844140,"streamedminutes":56623260,"uniquechannels":189105,"year":2019,"month":"march","language":"214"},{"viewminutes":2453706120,"streamedminutes":57007980,"uniquechannels":187033,"year":2019,"month":"april","language":"214"},{"viewminutes":2804769180,"streamedminutes":59455260,"uniquechannels":189736,"year":2019,"month":"may","language":"214"},{"viewminutes":2660938620,"streamedminutes":54074280,"uniquechannels":177237,"year":2019,"month":"june","language":"214"},{"viewminutes":2628035760,"streamedminutes":54588240,"uniquechannels":169994,"year":2019,"month":"july","language":"214"},{"viewminutes":2882064840,"streamedminutes":60840180,"uniquechannels":187819,"year":2019,"month":"august","language":"214"},{"viewminutes":3126685740,"streamedminutes":58025160,"uniquechannels":187334,"year":2019,"month":"september","language":"214"},{"viewminutes":2637808380,"streamedminutes":59283540,"uniquechannels":196621,"year":2019,"month":"october","language":"214"},{"viewminutes":2622786660,"streamedminutes":57352260,"uniquechannels":183912,"year":2019,"month":"november","language":"214"},{"viewminutes":2650978800,"streamedminutes":61064520,"uniquechannels":197256,"year":2019,"month":"december","language":"214"},{"viewminutes":2953253460,"streamedminutes":62170500,"uniquechannels":205766,"year":2020,"month":"january","language":"214"},{"viewminutes":2822892780,"streamedminutes":69351240,"uniquechannels":198669,"year":2020,"month":"february","language":"214"},{"viewminutes":3676523940,"streamedminutes":94170540,"uniquechannels":282000,"year":2020,"month":"march","language":"214"},{"viewminutes":6108003120,"streamedminutes":93988080,"uniquechannels":294726,"year":2020,"month":"april","language":"214"},{"viewminutes":6096286980,"streamedminutes":96112500,"uniquechannels":292635,"year":2020,"month":"may","language":"214"},{"viewminutes":5239095000,"streamedminutes":77958360,"uniquechannels":246512,"year":2020,"month":"june","language":"214"},{"viewminutes":4530664020,"streamedminutes":72328680,"uniquechannels":228210,"year":2020,"month":"july","language":"214"},{"viewminutes":3956655060,"streamedminutes":68243700,"uniquechannels":230226,"year":2020,"month":"august","language":"214"},{"viewminutes":4044081000,"streamedminutes":67883160,"uniquechannels":229618,"year":2020,"month":"september","language":"214"},{"viewminutes":5531404980,"streamedminutes":81818940,"uniquechannels":291083,"year":2020,"month":"october","language":"214"},{"viewminutes":5571450480,"streamedminutes":103744380,"uniquechannels":359400,"year":2020,"month":"november","language":"214"},{"viewminutes":4895437500,"streamedminutes":96148980,"uniquechannels":341366,"year":2020,"month":"december","language":"214"},{"viewminutes":6178187040,"streamedminutes":112691100,"uniquechannels":383330,"year":2021,"month":"january","language":"214"},{"viewminutes":5929489320,"streamedminutes":112899180,"uniquechannels":389791,"year":2021,"month":"february","language":"214"},{"viewminutes":6535409700,"streamedminutes":123989280,"uniquechannels":407589,"year":2021,"month":"march","language":"214"},{"viewminutes":1317426180,"streamedminutes":22610160,"uniquechannels":93205,"year":2016,"month":"january","language":"220"},{"viewminutes":1227852480,"streamedminutes":20569980,"uniquechannels":91758,"year":2016,"month":"february","language":"220"},{"viewminutes":1526954220,"streamedminutes":21791700,"uniquechannels":96389,"year":2016,"month":"march","language":"220"},{"viewminutes":1222186200,"streamedminutes":18184020,"uniquechannels":93579,"year":2016,"month":"april","language":"220"},{"viewminutes":1132988280,"streamedminutes":24639960,"uniquechannels":114069,"year":2016,"month":"may","language":"220"},{"viewminutes":1048607520,"streamedminutes":18189180,"uniquechannels":97928,"year":2016,"month":"june","language":"220"},{"viewminutes":1080434160,"streamedminutes":23641440,"uniquechannels":105793,"year":2016,"month":"july","language":"220"},{"viewminutes":1058068260,"streamedminutes":21149040,"uniquechannels":107319,"year":2016,"month":"august","language":"220"},{"viewminutes":916565400,"streamedminutes":26258940,"uniquechannels":108254,"year":2016,"month":"september","language":"220"},{"viewminutes":1164006000,"streamedminutes":26623020,"uniquechannels":125959,"year":2016,"month":"october","language":"220"},{"viewminutes":1188474780,"streamedminutes":21360480,"uniquechannels":121183,"year":2016,"month":"november","language":"220"},{"viewminutes":1178674680,"streamedminutes":30791580,"uniquechannels":39349,"year":2016,"month":"december","language":"220"},{"viewminutes":1411811400,"streamedminutes":36116940,"uniquechannels":170118,"year":2017,"month":"january","language":"220"},{"viewminutes":1305614280,"streamedminutes":29389200,"uniquechannels":146508,"year":2017,"month":"february","language":"220"},{"viewminutes":1213808040,"streamedminutes":22882620,"uniquechannels":125452,"year":2017,"month":"march","language":"220"},{"viewminutes":1186340760,"streamedminutes":23408160,"uniquechannels":126839,"year":2017,"month":"april","language":"220"},{"viewminutes":1422210720,"streamedminutes":41626320,"uniquechannels":152732,"year":2017,"month":"may","language":"220"},{"viewminutes":1529059320,"streamedminutes":41351940,"uniquechannels":153305,"year":2017,"month":"june","language":"220"},{"viewminutes":1618844220,"streamedminutes":45523560,"uniquechannels":165712,"year":2017,"month":"july","language":"220"},{"viewminutes":1311536400,"streamedminutes":41665500,"uniquechannels":161569,"year":2017,"month":"august","language":"220"},{"viewminutes":1404909960,"streamedminutes":40613580,"uniquechannels":157579,"year":2017,"month":"september","language":"220"},{"viewminutes":1694965740,"streamedminutes":46337280,"uniquechannels":177786,"year":2017,"month":"october","language":"220"},{"viewminutes":1729905900,"streamedminutes":43506900,"uniquechannels":164538,"year":2017,"month":"november","language":"220"},{"viewminutes":1539056700,"streamedminutes":46652460,"uniquechannels":182311,"year":2017,"month":"december","language":"220"},{"viewminutes":1782837180,"streamedminutes":53405040,"uniquechannels":210673,"year":2018,"month":"january","language":"220"},{"viewminutes":1577707500,"streamedminutes":49002240,"uniquechannels":194513,"year":2018,"month":"february","language":"220"},{"viewminutes":1781506320,"streamedminutes":54944040,"uniquechannels":222875,"year":2018,"month":"march","language":"220"},{"viewminutes":1699610820,"streamedminutes":60830820,"uniquechannels":202439,"year":2018,"month":"april","language":"220"},{"viewminutes":1920468480,"streamedminutes":69297420,"uniquechannels":214211,"year":2018,"month":"may","language":"220"},{"viewminutes":1812432960,"streamedminutes":62626500,"uniquechannels":205959,"year":2018,"month":"june","language":"220"},{"viewminutes":2039441280,"streamedminutes":64024560,"uniquechannels":202968,"year":2018,"month":"july","language":"220"},{"viewminutes":2057479620,"streamedminutes":68180580,"uniquechannels":214531,"year":2018,"month":"august","language":"220"},{"viewminutes":2082068160,"streamedminutes":69907560,"uniquechannels":219500,"year":2018,"month":"september","language":"220"},{"viewminutes":2422202700,"streamedminutes":74401440,"uniquechannels":232516,"year":2018,"month":"october","language":"220"},{"viewminutes":2041256940,"streamedminutes":66298980,"uniquechannels":220166,"year":2018,"month":"november","language":"220"},{"viewminutes":2288525040,"streamedminutes":81671940,"uniquechannels":255059,"year":2018,"month":"december","language":"220"},{"viewminutes":2751299700,"streamedminutes":87631320,"uniquechannels":278502,"year":2019,"month":"january","language":"220"},{"viewminutes":2404687140,"streamedminutes":78607500,"uniquechannels":260473,"year":2019,"month":"february","language":"220"},{"viewminutes":2592528840,"streamedminutes":87190140,"uniquechannels":268313,"year":2019,"month":"march","language":"220"},{"viewminutes":2430354120,"streamedminutes":83141700,"uniquechannels":248954,"year":2019,"month":"april","language":"220"},{"viewminutes":2557735560,"streamedminutes":87012900,"uniquechannels":253469,"year":2019,"month":"may","language":"220"},{"viewminutes":2518422420,"streamedminutes":80988120,"uniquechannels":242034,"year":2019,"month":"june","language":"220"},{"viewminutes":2564736420,"streamedminutes":84668340,"uniquechannels":240922,"year":2019,"month":"july","language":"220"},{"viewminutes":2796623220,"streamedminutes":90313380,"uniquechannels":260641,"year":2019,"month":"august","language":"220"},{"viewminutes":2908031760,"streamedminutes":90167340,"uniquechannels":255412,"year":2019,"month":"september","language":"220"},{"viewminutes":2683932360,"streamedminutes":88359720,"uniquechannels":265858,"year":2019,"month":"october","language":"220"},{"viewminutes":2897178960,"streamedminutes":84448560,"uniquechannels":256939,"year":2019,"month":"november","language":"220"},{"viewminutes":2980673280,"streamedminutes":93130200,"uniquechannels":278980,"year":2019,"month":"december","language":"220"},{"viewminutes":3285505260,"streamedminutes":92668740,"uniquechannels":291592,"year":2020,"month":"january","language":"220"},{"viewminutes":3143355600,"streamedminutes":106084680,"uniquechannels":282546,"year":2020,"month":"february","language":"220"},{"viewminutes":3861211560,"streamedminutes":135370740,"uniquechannels":368732,"year":2020,"month":"march","language":"220"},{"viewminutes":5189293440,"streamedminutes":127387080,"uniquechannels":380171,"year":2020,"month":"april","language":"220"},{"viewminutes":5256331320,"streamedminutes":136191600,"uniquechannels":390399,"year":2020,"month":"may","language":"220"},{"viewminutes":4890066900,"streamedminutes":118867500,"uniquechannels":348262,"year":2020,"month":"june","language":"220"},{"viewminutes":5058817800,"streamedminutes":117520260,"uniquechannels":343203,"year":2020,"month":"july","language":"220"},{"viewminutes":4389829320,"streamedminutes":112537500,"uniquechannels":343713,"year":2020,"month":"august","language":"220"},{"viewminutes":4086702060,"streamedminutes":108766920,"uniquechannels":328168,"year":2020,"month":"september","language":"220"},{"viewminutes":5453763420,"streamedminutes":124702740,"uniquechannels":384186,"year":2020,"month":"october","language":"220"},{"viewminutes":5774109180,"streamedminutes":132574920,"uniquechannels":411489,"year":2020,"month":"november","language":"220"},{"viewminutes":5738668200,"streamedminutes":146818620,"uniquechannels":461982,"year":2020,"month":"december","language":"220"},{"viewminutes":7524723900,"streamedminutes":176523780,"uniquechannels":549647,"year":2021,"month":"january","language":"220"},{"viewminutes":7368611940,"streamedminutes":169978500,"uniquechannels":530744,"year":2021,"month":"february","language":"220"},{"viewminutes":7528745340,"streamedminutes":183203340,"uniquechannels":554114,"year":2021,"month":"march","language":"220"},{"viewminutes":54138540,"streamedminutes":1211460,"uniquechannels":6301,"year":2016,"month":"january","language":"230"},{"viewminutes":66324420,"streamedminutes":1257960,"uniquechannels":6878,"year":2016,"month":"february","language":"230"},{"viewminutes":67367040,"streamedminutes":1412100,"uniquechannels":7501,"year":2016,"month":"march","language":"230"},{"viewminutes":57614580,"streamedminutes":1317180,"uniquechannels":7766,"year":2016,"month":"april","language":"230"},{"viewminutes":63350220,"streamedminutes":1590300,"uniquechannels":8946,"year":2016,"month":"may","language":"230"},{"viewminutes":70138680,"streamedminutes":1272420,"uniquechannels":8423,"year":2016,"month":"june","language":"230"},{"viewminutes":54653220,"streamedminutes":1443900,"uniquechannels":8134,"year":2016,"month":"july","language":"230"},{"viewminutes":51400980,"streamedminutes":1272360,"uniquechannels":8161,"year":2016,"month":"august","language":"230"},{"viewminutes":72250920,"streamedminutes":1960740,"uniquechannels":10702,"year":2016,"month":"september","language":"230"},{"viewminutes":64608840,"streamedminutes":1794360,"uniquechannels":11234,"year":2016,"month":"october","language":"230"},{"viewminutes":67791780,"streamedminutes":1564320,"uniquechannels":11693,"year":2016,"month":"november","language":"230"},{"viewminutes":72957840,"streamedminutes":2244660,"uniquechannels":3901,"year":2016,"month":"december","language":"230"},{"viewminutes":98286420,"streamedminutes":2769660,"uniquechannels":15690,"year":2017,"month":"january","language":"230"},{"viewminutes":87359280,"streamedminutes":2386500,"uniquechannels":14856,"year":2017,"month":"february","language":"230"},{"viewminutes":88872900,"streamedminutes":1839600,"uniquechannels":12892,"year":2017,"month":"march","language":"230"},{"viewminutes":78035580,"streamedminutes":1816260,"uniquechannels":12695,"year":2017,"month":"april","language":"230"},{"viewminutes":100380660,"streamedminutes":3832920,"uniquechannels":17292,"year":2017,"month":"may","language":"230"},{"viewminutes":105637680,"streamedminutes":3644040,"uniquechannels":17064,"year":2017,"month":"june","language":"230"},{"viewminutes":113997540,"streamedminutes":3678120,"uniquechannels":17404,"year":2017,"month":"july","language":"230"},{"viewminutes":93607560,"streamedminutes":3043620,"uniquechannels":15458,"year":2017,"month":"august","language":"230"},{"viewminutes":113904720,"streamedminutes":3386160,"uniquechannels":17523,"year":2017,"month":"september","language":"230"},{"viewminutes":118678080,"streamedminutes":3774360,"uniquechannels":18757,"year":2017,"month":"october","language":"230"},{"viewminutes":115700760,"streamedminutes":3753960,"uniquechannels":18117,"year":2017,"month":"november","language":"230"},{"viewminutes":123216240,"streamedminutes":3967320,"uniquechannels":20096,"year":2017,"month":"december","language":"230"},{"viewminutes":149372460,"streamedminutes":4856520,"uniquechannels":23170,"year":2018,"month":"january","language":"230"},{"viewminutes":135197040,"streamedminutes":4630920,"uniquechannels":22152,"year":2018,"month":"february","language":"230"},{"viewminutes":151566420,"streamedminutes":5125320,"uniquechannels":26053,"year":2018,"month":"march","language":"230"},{"viewminutes":161021820,"streamedminutes":6126780,"uniquechannels":25295,"year":2018,"month":"april","language":"230"},{"viewminutes":202381080,"streamedminutes":7429500,"uniquechannels":28814,"year":2018,"month":"may","language":"230"},{"viewminutes":209235960,"streamedminutes":6892560,"uniquechannels":28470,"year":2018,"month":"june","language":"230"},{"viewminutes":220397400,"streamedminutes":6781680,"uniquechannels":27626,"year":2018,"month":"july","language":"230"},{"viewminutes":251379840,"streamedminutes":7403040,"uniquechannels":30318,"year":2018,"month":"august","language":"230"},{"viewminutes":298532160,"streamedminutes":8568540,"uniquechannels":34940,"year":2018,"month":"september","language":"230"},{"viewminutes":367707420,"streamedminutes":9269940,"uniquechannels":34894,"year":2018,"month":"october","language":"230"},{"viewminutes":432654960,"streamedminutes":10088520,"uniquechannels":39363,"year":2018,"month":"november","language":"230"},{"viewminutes":470285040,"streamedminutes":11591040,"uniquechannels":41898,"year":2018,"month":"december","language":"230"},{"viewminutes":532260540,"streamedminutes":12740100,"uniquechannels":46944,"year":2019,"month":"january","language":"230"},{"viewminutes":446323920,"streamedminutes":11979240,"uniquechannels":45515,"year":2019,"month":"february","language":"230"},{"viewminutes":525314700,"streamedminutes":13081500,"uniquechannels":46899,"year":2019,"month":"march","language":"230"},{"viewminutes":507624420,"streamedminutes":13372980,"uniquechannels":47081,"year":2019,"month":"april","language":"230"},{"viewminutes":531782640,"streamedminutes":14457060,"uniquechannels":48135,"year":2019,"month":"may","language":"230"},{"viewminutes":537430860,"streamedminutes":13848780,"uniquechannels":48059,"year":2019,"month":"june","language":"230"},{"viewminutes":503335440,"streamedminutes":14404440,"uniquechannels":46858,"year":2019,"month":"july","language":"230"},{"viewminutes":468516240,"streamedminutes":13639200,"uniquechannels":45906,"year":2019,"month":"august","language":"230"},{"viewminutes":519447660,"streamedminutes":15507600,"uniquechannels":53039,"year":2019,"month":"september","language":"230"},{"viewminutes":590736720,"streamedminutes":14895120,"uniquechannels":51091,"year":2019,"month":"october","language":"230"},{"viewminutes":583268460,"streamedminutes":14771580,"uniquechannels":49615,"year":2019,"month":"november","language":"230"},{"viewminutes":550781640,"streamedminutes":14989860,"uniquechannels":50478,"year":2019,"month":"december","language":"230"},{"viewminutes":679750500,"streamedminutes":15754080,"uniquechannels":53965,"year":2020,"month":"january","language":"230"},{"viewminutes":670940400,"streamedminutes":17777520,"uniquechannels":52914,"year":2020,"month":"february","language":"230"},{"viewminutes":1093848540,"streamedminutes":29841600,"uniquechannels":94165,"year":2020,"month":"march","language":"230"},{"viewminutes":1808904300,"streamedminutes":31522260,"uniquechannels":105460,"year":2020,"month":"april","language":"230"},{"viewminutes":2037854100,"streamedminutes":36189060,"uniquechannels":119277,"year":2020,"month":"may","language":"230"},{"viewminutes":1593105240,"streamedminutes":30087360,"uniquechannels":103869,"year":2020,"month":"june","language":"230"},{"viewminutes":1226307840,"streamedminutes":25527960,"uniquechannels":86696,"year":2020,"month":"july","language":"230"},{"viewminutes":1162743060,"streamedminutes":21389880,"uniquechannels":78198,"year":2020,"month":"august","language":"230"},{"viewminutes":1397068020,"streamedminutes":24582180,"uniquechannels":91927,"year":2020,"month":"september","language":"230"},{"viewminutes":1622589240,"streamedminutes":26551680,"uniquechannels":97927,"year":2020,"month":"october","language":"230"},{"viewminutes":2150747520,"streamedminutes":35321520,"uniquechannels":134877,"year":2020,"month":"november","language":"230"},{"viewminutes":2223359040,"streamedminutes":38298360,"uniquechannels":152503,"year":2020,"month":"december","language":"230"},{"viewminutes":2817212340,"streamedminutes":45627300,"uniquechannels":172021,"year":2021,"month":"january","language":"230"},{"viewminutes":2467846380,"streamedminutes":41172000,"uniquechannels":152681,"year":2021,"month":"february","language":"230"},{"viewminutes":3196365720,"streamedminutes":51709620,"uniquechannels":181946,"year":2021,"month":"march","language":"230"},{"viewminutes":411902760,"streamedminutes":6799320,"uniquechannels":36931,"year":2016,"month":"january","language":"228"},{"viewminutes":401255100,"streamedminutes":6060540,"uniquechannels":35026,"year":2016,"month":"february","language":"228"},{"viewminutes":392119380,"streamedminutes":6493440,"uniquechannels":36736,"year":2016,"month":"march","language":"228"},{"viewminutes":351095760,"streamedminutes":5490240,"uniquechannels":36429,"year":2016,"month":"april","language":"228"},{"viewminutes":319303320,"streamedminutes":6868500,"uniquechannels":40872,"year":2016,"month":"may","language":"228"},{"viewminutes":400900500,"streamedminutes":5492820,"uniquechannels":39039,"year":2016,"month":"june","language":"228"},{"viewminutes":391809600,"streamedminutes":7698960,"uniquechannels":45355,"year":2016,"month":"july","language":"228"},{"viewminutes":409186560,"streamedminutes":6912420,"uniquechannels":43618,"year":2016,"month":"august","language":"228"},{"viewminutes":402927120,"streamedminutes":8959920,"uniquechannels":46997,"year":2016,"month":"september","language":"228"},{"viewminutes":567092580,"streamedminutes":8613060,"uniquechannels":49611,"year":2016,"month":"october","language":"228"},{"viewminutes":411945360,"streamedminutes":7452720,"uniquechannels":50561,"year":2016,"month":"november","language":"228"},{"viewminutes":480795180,"streamedminutes":10337520,"uniquechannels":16533,"year":2016,"month":"december","language":"228"},{"viewminutes":585242520,"streamedminutes":12062220,"uniquechannels":71492,"year":2017,"month":"january","language":"228"},{"viewminutes":508138440,"streamedminutes":10304760,"uniquechannels":62907,"year":2017,"month":"february","language":"228"},{"viewminutes":563247960,"streamedminutes":7836480,"uniquechannels":53853,"year":2017,"month":"march","language":"228"},{"viewminutes":500502480,"streamedminutes":8059140,"uniquechannels":54661,"year":2017,"month":"april","language":"228"},{"viewminutes":621214620,"streamedminutes":15729240,"uniquechannels":73064,"year":2017,"month":"may","language":"228"},{"viewminutes":648034020,"streamedminutes":15519060,"uniquechannels":73659,"year":2017,"month":"june","language":"228"},{"viewminutes":643974840,"streamedminutes":18128820,"uniquechannels":84928,"year":2017,"month":"july","language":"228"},{"viewminutes":742683300,"streamedminutes":16744920,"uniquechannels":80212,"year":2017,"month":"august","language":"228"},{"viewminutes":746946000,"streamedminutes":16803780,"uniquechannels":84466,"year":2017,"month":"september","language":"228"},{"viewminutes":811661580,"streamedminutes":18364020,"uniquechannels":92390,"year":2017,"month":"october","language":"228"},{"viewminutes":762118320,"streamedminutes":18551760,"uniquechannels":93776,"year":2017,"month":"november","language":"228"},{"viewminutes":802395120,"streamedminutes":20620680,"uniquechannels":115667,"year":2017,"month":"december","language":"228"},{"viewminutes":962331180,"streamedminutes":25547280,"uniquechannels":138039,"year":2018,"month":"january","language":"228"},{"viewminutes":932321220,"streamedminutes":25073520,"uniquechannels":132246,"year":2018,"month":"february","language":"228"},{"viewminutes":1119297600,"streamedminutes":29172120,"uniquechannels":152055,"year":2018,"month":"march","language":"228"},{"viewminutes":1174144500,"streamedminutes":36131220,"uniquechannels":155605,"year":2018,"month":"april","language":"228"},{"viewminutes":1300080660,"streamedminutes":42263700,"uniquechannels":167625,"year":2018,"month":"may","language":"228"},{"viewminutes":1292103900,"streamedminutes":41346540,"uniquechannels":178939,"year":2018,"month":"june","language":"228"},{"viewminutes":1327653840,"streamedminutes":45825360,"uniquechannels":193477,"year":2018,"month":"july","language":"228"},{"viewminutes":1451692800,"streamedminutes":50003820,"uniquechannels":206516,"year":2018,"month":"august","language":"228"},{"viewminutes":1362022200,"streamedminutes":51789960,"uniquechannels":211022,"year":2018,"month":"september","language":"228"},{"viewminutes":1445326200,"streamedminutes":51272640,"uniquechannels":200069,"year":2018,"month":"october","language":"228"},{"viewminutes":1251680640,"streamedminutes":47439180,"uniquechannels":200340,"year":2018,"month":"november","language":"228"},{"viewminutes":1510311660,"streamedminutes":56385120,"uniquechannels":227580,"year":2018,"month":"december","language":"228"},{"viewminutes":1731439200,"streamedminutes":61130940,"uniquechannels":250851,"year":2019,"month":"january","language":"228"},{"viewminutes":1532254260,"streamedminutes":57571860,"uniquechannels":241209,"year":2019,"month":"february","language":"228"},{"viewminutes":1540964700,"streamedminutes":62849880,"uniquechannels":245944,"year":2019,"month":"march","language":"228"},{"viewminutes":1531417860,"streamedminutes":63030420,"uniquechannels":236187,"year":2019,"month":"april","language":"228"},{"viewminutes":1590916740,"streamedminutes":64259220,"uniquechannels":229881,"year":2019,"month":"may","language":"228"},{"viewminutes":1568758560,"streamedminutes":65084820,"uniquechannels":241322,"year":2019,"month":"june","language":"228"},{"viewminutes":1532005800,"streamedminutes":71319120,"uniquechannels":254833,"year":2019,"month":"july","language":"228"},{"viewminutes":1791422400,"streamedminutes":73935120,"uniquechannels":262326,"year":2019,"month":"august","language":"228"},{"viewminutes":1773402240,"streamedminutes":73732860,"uniquechannels":255692,"year":2019,"month":"september","language":"228"},{"viewminutes":1941014220,"streamedminutes":67998480,"uniquechannels":249782,"year":2019,"month":"october","language":"228"},{"viewminutes":1886792100,"streamedminutes":69524700,"uniquechannels":257546,"year":2019,"month":"november","language":"228"},{"viewminutes":2074257240,"streamedminutes":79903680,"uniquechannels":293667,"year":2019,"month":"december","language":"228"},{"viewminutes":2732649660,"streamedminutes":89293080,"uniquechannels":337180,"year":2020,"month":"january","language":"228"},{"viewminutes":2797314540,"streamedminutes":94170420,"uniquechannels":318486,"year":2020,"month":"february","language":"228"},{"viewminutes":3772149480,"streamedminutes":125469720,"uniquechannels":455061,"year":2020,"month":"march","language":"228"},{"viewminutes":6537860700,"streamedminutes":137573820,"uniquechannels":512225,"year":2020,"month":"april","language":"228"},{"viewminutes":9024161520,"streamedminutes":176178360,"uniquechannels":666408,"year":2020,"month":"may","language":"228"},{"viewminutes":8312947620,"streamedminutes":173678640,"uniquechannels":694699,"year":2020,"month":"june","language":"228"},{"viewminutes":9053981760,"streamedminutes":187733940,"uniquechannels":732273,"year":2020,"month":"july","language":"228"},{"viewminutes":9563147760,"streamedminutes":197394360,"uniquechannels":828823,"year":2020,"month":"august","language":"228"},{"viewminutes":10225133820,"streamedminutes":199399740,"uniquechannels":870370,"year":2020,"month":"september","language":"228"},{"viewminutes":10901456520,"streamedminutes":218528760,"uniquechannels":939171,"year":2020,"month":"october","language":"228"},{"viewminutes":10377868380,"streamedminutes":219677640,"uniquechannels":951164,"year":2020,"month":"november","language":"228"},{"viewminutes":9879581040,"streamedminutes":219981780,"uniquechannels":969166,"year":2020,"month":"december","language":"228"},{"viewminutes":13111451400,"streamedminutes":263861040,"uniquechannels":1115676,"year":2021,"month":"january","language":"228"},{"viewminutes":10883426340,"streamedminutes":265555740,"uniquechannels":1118194,"year":2021,"month":"february","language":"228"},{"viewminutes":11418143400,"streamedminutes":287994060,"uniquechannels":1184678,"year":2021,"month":"march","language":"228"},{"viewminutes":28824882060,"streamedminutes":797586420,"uniquechannels":2249893,"year":2016,"month":"january","language":"000"},{"viewminutes":26332002420,"streamedminutes":764309760,"uniquechannels":2126301,"year":2016,"month":"february","language":"000"},{"viewminutes":29342444640,"streamedminutes":811261020,"uniquechannels":2205382,"year":2016,"month":"march","language":"000"},{"viewminutes":27917518200,"streamedminutes":802242780,"uniquechannels":2105311,"year":2016,"month":"april","language":"000"},{"viewminutes":27054370260,"streamedminutes":804895620,"uniquechannels":2322646,"year":2016,"month":"may","language":"000"},{"viewminutes":26724190860,"streamedminutes":764038620,"uniquechannels":2149169,"year":2016,"month":"june","language":"000"},{"viewminutes":27283423260,"streamedminutes":771521940,"uniquechannels":2313493,"year":2016,"month":"july","language":"000"},{"viewminutes":25857155340,"streamedminutes":791744040,"uniquechannels":2232176,"year":2016,"month":"august","language":"000"},{"viewminutes":23054964480,"streamedminutes":718033080,"uniquechannels":2105871,"year":2016,"month":"september","language":"000"},{"viewminutes":27043496820,"streamedminutes":777044400,"uniquechannels":2140326,"year":2016,"month":"october","language":"000"},{"viewminutes":26718215100,"streamedminutes":793530300,"uniquechannels":1967098,"year":2016,"month":"november","language":"000"},{"viewminutes":29120601360,"streamedminutes":903772260,"uniquechannels":598676,"year":2016,"month":"december","language":"000"},{"viewminutes":35924485440,"streamedminutes":973328460,"uniquechannels":2631349,"year":2017,"month":"january","language":"000"},{"viewminutes":29882049600,"streamedminutes":887339700,"uniquechannels":2268942,"year":2017,"month":"february","language":"000"},{"viewminutes":30789091380,"streamedminutes":917046720,"uniquechannels":1894789,"year":2017,"month":"march","language":"000"},{"viewminutes":31870268700,"streamedminutes":869358240,"uniquechannels":1807668,"year":2017,"month":"april","language":"000"},{"viewminutes":30278537880,"streamedminutes":919004880,"uniquechannels":2475640,"year":2017,"month":"may","language":"000"},{"viewminutes":30515775180,"streamedminutes":928280820,"uniquechannels":2540106,"year":2017,"month":"june","language":"000"},{"viewminutes":34046596380,"streamedminutes":1044756480,"uniquechannels":2711754,"year":2017,"month":"july","language":"000"},{"viewminutes":31913340240,"streamedminutes":1009981860,"uniquechannels":2565651,"year":2017,"month":"august","language":"000"},{"viewminutes":31610016660,"streamedminutes":1000757640,"uniquechannels":2423073,"year":2017,"month":"september","language":"000"},{"viewminutes":34997262480,"streamedminutes":1045154880,"uniquechannels":2609724,"year":2017,"month":"october","language":"000"},{"viewminutes":34409333580,"streamedminutes":1027257360,"uniquechannels":2563092,"year":2017,"month":"november","language":"000"},{"viewminutes":34183466940,"streamedminutes":1138716120,"uniquechannels":2843633,"year":2017,"month":"december","language":"000"},{"viewminutes":43326363720,"streamedminutes":1362664980,"uniquechannels":3326401,"year":2018,"month":"january","language":"000"},{"viewminutes":36805525800,"streamedminutes":1312278300,"uniquechannels":3145150,"year":2018,"month":"february","language":"000"},{"viewminutes":43063532400,"streamedminutes":1574849760,"uniquechannels":3795722,"year":2018,"month":"march","language":"000"},{"viewminutes":43635020040,"streamedminutes":1591149840,"uniquechannels":3821791,"year":2018,"month":"april","language":"000"},{"viewminutes":45383294460,"streamedminutes":1612028700,"uniquechannels":3933827,"year":2018,"month":"may","language":"000"},{"viewminutes":46809581220,"streamedminutes":1592365740,"uniquechannels":4032937,"year":2018,"month":"june","language":"000"},{"viewminutes":47468340420,"streamedminutes":1726059660,"uniquechannels":4135590,"year":2018,"month":"july","language":"000"},{"viewminutes":50888629860,"streamedminutes":1842178320,"uniquechannels":4385410,"year":2018,"month":"august","language":"000"},{"viewminutes":48223051920,"streamedminutes":1768195620,"uniquechannels":4200711,"year":2018,"month":"september","language":"000"},{"viewminutes":50187527100,"streamedminutes":1739126580,"uniquechannels":4221234,"year":2018,"month":"october","language":"000"},{"viewminutes":49863688920,"streamedminutes":1729449840,"uniquechannels":4154109,"year":2018,"month":"november","language":"000"},{"viewminutes":50189180400,"streamedminutes":1975434960,"uniquechannels":4622319,"year":2018,"month":"december","language":"000"},{"viewminutes":56043469980,"streamedminutes":2301613200,"uniquechannels":4942773,"year":2019,"month":"january","language":"000"},{"viewminutes":52094378340,"streamedminutes":2076347040,"uniquechannels":4692575,"year":2019,"month":"february","language":"000"},{"viewminutes":56093279400,"streamedminutes":2238147300,"uniquechannels":4885414,"year":2019,"month":"march","language":"000"},{"viewminutes":52549437120,"streamedminutes":2027301840,"uniquechannels":4666108,"year":2019,"month":"april","language":"000"},{"viewminutes":55607512920,"streamedminutes":1986633540,"uniquechannels":4609927,"year":2019,"month":"may","language":"000"},{"viewminutes":55620932760,"streamedminutes":1907703960,"uniquechannels":4423851,"year":2019,"month":"june","language":"000"},{"viewminutes":54292666200,"streamedminutes":1979584020,"uniquechannels":4380314,"year":2019,"month":"july","language":"000"},{"viewminutes":59386564200,"streamedminutes":1999695000,"uniquechannels":4380603,"year":2019,"month":"august","language":"000"},{"viewminutes":52143595920,"streamedminutes":1838071440,"uniquechannels":4004687,"year":2019,"month":"september","language":"000"},{"viewminutes":53518379160,"streamedminutes":1863385800,"uniquechannels":3928864,"year":2019,"month":"october","language":"000"},{"viewminutes":52041346320,"streamedminutes":1790623500,"uniquechannels":3880842,"year":2019,"month":"november","language":"000"},{"viewminutes":52511974500,"streamedminutes":1885520940,"uniquechannels":4290669,"year":2019,"month":"december","language":"000"},{"viewminutes":60249025500,"streamedminutes":2186773680,"uniquechannels":4680959,"year":2020,"month":"january","language":"000"},{"viewminutes":58339718820,"streamedminutes":2069370060,"uniquechannels":4254725,"year":2020,"month":"february","language":"000"},{"viewminutes":72302499360,"streamedminutes":2715990480,"uniquechannels":5648840,"year":2020,"month":"march","language":"000"},{"viewminutes":106631528760,"streamedminutes":3744725520,"uniquechannels":6042562,"year":2020,"month":"april","language":"000"},{"viewminutes":104327084280,"streamedminutes":4160658600,"uniquechannels":6612288,"year":2020,"month":"may","language":"000"},{"viewminutes":96841808700,"streamedminutes":3730257900,"uniquechannels":6107092,"year":2020,"month":"june","language":"000"},{"viewminutes":93437998680,"streamedminutes":3934749000,"uniquechannels":6424545,"year":2020,"month":"july","language":"000"},{"viewminutes":96339062880,"streamedminutes":3910731240,"uniquechannels":6739249,"year":2020,"month":"august","language":"000"},{"viewminutes":94263619440,"streamedminutes":3716800260,"uniquechannels":6705300,"year":2020,"month":"september","language":"000"},{"viewminutes":105753575460,"streamedminutes":4047149520,"uniquechannels":7383820,"year":2020,"month":"october","language":"000"},{"viewminutes":106707846960,"streamedminutes":4200361920,"uniquechannels":7583756,"year":2020,"month":"november","language":"000"},{"viewminutes":111862149780,"streamedminutes":4467197460,"uniquechannels":7975254,"year":2020,"month":"december","language":"000"},{"viewminutes":129881099340,"streamedminutes":5008855680,"uniquechannels":8923704,"year":2021,"month":"january","language":"000"},{"viewminutes":118302846000,"streamedminutes":4680735240,"uniquechannels":8460647,"year":2021,"month":"february","language":"000"},{"viewminutes":130127701620,"streamedminutes":4958934840,"uniquechannels":8875837,"year":2021,"month":"march","language":"000"}]